wendata/__init__.py
wendata/wendata.py
wendata-1.0.dist-info/LICENSE.txt
wendata-1.0.dist-info/METADATA
wendata-1.0.dist-info/WHEEL
wendata-1.0.dist-info/top_level.txt
wendata-1.0.dist-info/RECORD
