Metadata-Version: 2.1
Name: wendata
Version: 1.0
Summary: package for research
Home-page: http://github.com/wenchenk/wendata.git
Author: ck
Author-email: 943250846@qq.com
License: UNKNOWN
Platform: UNKNOWN
Classifier: Programming Language :: Python :: 3.8
Classifier: License :: OSI Approved :: MIT License
Classifier: Operating System :: Microsoft :: Windows :: Windows 10
